odoo10_addon_website_event_share-10.0.1.0.0-py2.7-nspkg.pth
odoo/addons/website_event_share/README.rst
odoo/addons/website_event_share/__init__.py
odoo/addons/website_event_share/__manifest__.py
odoo/addons/website_event_share/static/description/icon.png
odoo/addons/website_event_share/views/website_event.xml
odoo10_addon_website_event_share-10.0.1.0.0.dist-info/DESCRIPTION.rst
odoo10_addon_website_event_share-10.0.1.0.0.dist-info/METADATA
odoo10_addon_website_event_share-10.0.1.0.0.dist-info/RECORD
odoo10_addon_website_event_share-10.0.1.0.0.dist-info/WHEEL
odoo10_addon_website_event_share-10.0.1.0.0.dist-info/metadata.json
odoo10_addon_website_event_share-10.0.1.0.0.dist-info/namespace_packages.txt
odoo10_addon_website_event_share-10.0.1.0.0.dist-info/top_level.txt
