Metadata-Version: 2.0
Name: odoo10-addon-website-event-share
Version: 10.0.1.0.0
Summary: Add contacts to event
Home-page: https://opensynergy-indonesia.com
Author: OpenSynergy Indonesia,Tecnativa, Odoo Community Association (OCA)
Author-email: support@odoo-community.org
License: AGPL-3
Platform: UNKNOWN
Classifier: Programming Language :: Python :: 2.7
Classifier: Framework :: Odoo
Classifier: License :: OSI Approved :: GNU Affero General Public License v3
Requires-Dist: odoo (<10.1dev,>=10.0)
